gaama/__init__.py
gaama/exceptions.py
gaama/gaama.py
gaama/github.py
gaama/version.py
gaama-0.7.2.dist-info/licenses/LICENSE
gaama-0.7.2.dist-info/METADATA
gaama-0.7.2.dist-info/WHEEL
gaama-0.7.2.dist-info/top_level.txt
gaama-0.7.2.dist-info/zip-safe
gaama-0.7.2.dist-info/RECORD
