Metadata-Version: 2.4
Name: gaama
Version: 0.7.2
Summary: GitHub-as-Artifactory for Model Artifacts
Home-page: https://github.com/prabhuomkar/bitbeast
Author: Omkar Prabhu
Author-email: prabhuomkar@pm.me
License: Apache-2.0
Classifier: Development Status :: 3 - Alpha
Classifier: Programming Language :: Python :: 3
Classifier: Intended Audience :: Science/Research
Classifier: Topic :: Scientific/Engineering :: Artificial Intelligence
License-File: LICENSE
Requires-Dist: requests
Dynamic: author
Dynamic: author-email
Dynamic: classifier
Dynamic: description
Dynamic: description-content-type
Dynamic: home-page
Dynamic: license
Dynamic: license-file
Dynamic: requires-dist
Dynamic: summary
